{"commodities": [{"name": "Gold", "price": 4755.8999, "change": -21.1001, "pct": -0.44}, {"name": "Silver", "price": 77.66, "change": -0.425, "pct": -0.54}, {"name": "Crude Oil", "price": 92.7, "change": 3.45, "pct": 3.87}, {"name": "Natural Gas", "price": 2.713, "change": -0.001, "pct": -0.04}, {"name": "Copper", "price": 6.134, "change": 0.0915, "pct": 1.51}, {"name": "Platinum", "price": 2087.1001, "change": 11.2002, "pct": 0.54}], "crypto": [{"name": "Bitcoin", "price": 78467.6328, "change": 2120.8203, "pct": 2.78}, {"name": "Ethereum", "price": 2391.75, "change": 63.76, "pct": 2.74}, {"name": "Binance", "price": 641.56, "change": 9.61, "pct": 1.52}, {"name": "Cardano", "price": 0.2515, "change": 0.0016, "pct": 0.64}, {"name": "Solana", "price": 87.15, "change": 1.08, "pct": 1.25}, {"name": "XRP", "price": 1.4377, "change": 0.0033, "pct": 0.23}, {"name": "Polkadot", "price": 1.274, "change": -0.005, "pct": -0.39}, {"name": "Avalanche", "price": 9.46, "change": 0.07, "pct": 0.75}, {"name": "Litecoin", "price": 55.83, "change": 0.23, "pct": 0.41}, {"name": "Algorand", "price": 0.104, "change": 0.0006, "pct": 0.58}, {"name": "Bitcoin Cash", "price": 462.51, "change": 13.78, "pct": 3.07}], "updated": "2026-04-22 20:54 UTC"}