{"commodities": [{"name": "Gold", "price": 4783.7002, "change": -2.5996, "pct": -0.05}, {"name": "Silver", "price": 76.71, "change": 0.76, "pct": 1.0}, {"name": "Crude Oil", "price": 97.32, "change": 0.2, "pct": 0.21}, {"name": "Natural Gas", "price": 2.605, "change": -0.014, "pct": -0.53}, {"name": "Copper", "price": 6.0035, "change": -0.0115, "pct": -0.19}, {"name": "Platinum", "price": 2088.2, "change": -4.5, "pct": -0.22}], "crypto": [{"name": "Bitcoin", "price": 74326.375, "change": -206.3672, "pct": -0.28}, {"name": "Ethereum", "price": 2363.51, "change": -6.5901, "pct": -0.28}, {"name": "Binance", "price": 612.8712, "change": -2.1872, "pct": -0.36}, {"name": "Cardano", "price": 0.2429, "change": -0.0057, "pct": -2.29}, {"name": "Solana", "price": 85.7879, "change": -0.8859, "pct": -1.02}, {"name": "XRP", "price": 1.3653, "change": -0.0115, "pct": -0.84}, {"name": "Polkadot", "price": 1.1909, "change": -0.0397, "pct": -3.23}, {"name": "Avalanche", "price": 9.4213, "change": -0.2494, "pct": -2.58}, {"name": "Litecoin", "price": 54.1243, "change": -0.5299, "pct": -0.97}, {"name": "Algorand", "price": 0.1127, "change": 0.0034, "pct": 3.11}, {"name": "Bitcoin Cash", "price": 437.4844, "change": -1.183, "pct": -0.27}], "updated": "2026-04-14 05:44 UTC"}