{"commodities": [{"name": "Gold", "price": 4771.2998, "change": -5.7002, "pct": -0.12}, {"name": "Silver", "price": 78.18, "change": 0.095, "pct": 0.12}, {"name": "Crude Oil", "price": 91.68, "change": 2.43, "pct": 2.72}, {"name": "Natural Gas", "price": 2.741, "change": 0.027, "pct": 0.99}, {"name": "Copper", "price": 6.063, "change": 0.0205, "pct": 0.34}, {"name": "Platinum", "price": 2096.7, "change": 20.8, "pct": 1.0}], "crypto": [{"name": "Bitcoin", "price": 78932.0, "change": 2576.0, "pct": 3.37}, {"name": "Ethereum", "price": 2421.1899, "change": 93.2, "pct": 4.0}, {"name": "Binance", "price": 651.83, "change": 19.88, "pct": 3.15}, {"name": "Cardano", "price": 0.2553, "change": 0.0054, "pct": 2.16}, {"name": "Solana", "price": 89.17, "change": 3.1, "pct": 3.6}, {"name": "XRP", "price": 1.4589, "change": 0.0245, "pct": 1.71}, {"name": "Polkadot", "price": 1.302, "change": 0.023, "pct": 1.8}, {"name": "Avalanche", "price": 9.57, "change": 0.18, "pct": 1.92}, {"name": "Litecoin", "price": 56.29, "change": 0.69, "pct": 1.24}, {"name": "Algorand", "price": 0.1049, "change": 0.0015, "pct": 1.45}, {"name": "Bitcoin Cash", "price": 464.37, "change": 15.64, "pct": 3.49}], "updated": "2026-04-22 14:04 UTC"}